datalogd/__init__.py
datalogd/__main__.py
datalogd/plugins/__init__.py
datalogd/plugins/aggregator_datafilter.py
datalogd/plugins/coolingpower_datafilter.py
datalogd/plugins/csv_datafilter.py
datalogd/plugins/file_datasink.py
datalogd/plugins/flowsensorcalibration_datafilter.py
datalogd/plugins/heartbeat_datasource.py
datalogd/plugins/influxdb2_datasink.py
datalogd/plugins/influxdb_datasink.py
datalogd/plugins/join_datafilter.py
datalogd/plugins/keyval_datafilter.py
datalogd/plugins/libsensors_datasource.py
datalogd/plugins/logging_datasink.py
datalogd/plugins/logwidget.ui
datalogd/plugins/matplotlib_datasink.py
datalogd/plugins/picotc08_datasource.py
datalogd/plugins/polynomialfunction_datafilter.py
datalogd/plugins/print_datasink.py
datalogd/plugins/pyqtgraph_datasink.py
datalogd/plugins/randomwalk_datasource.py
datalogd/plugins/resources_rc.py
datalogd/plugins/sensoridentifierdatafilter.py
datalogd/plugins/sensorpaneldatafilter.py
datalogd/plugins/sensorpaneldatafilter_demo.ui
datalogd/plugins/sensorwidget.ui
datalogd/plugins/serial_datasource.py
datalogd/plugins/sinktimer_datafilter.py
datalogd/plugins/socket_datafilter.py
datalogd/plugins/thorlabspm100_datasource.py
datalogd/plugins/timestamp_datafilter.py
datalogd/plugins/watchdogwidget.ui
datalogd-0.4.2.dist-info/LICENSE.txt
datalogd-0.4.2.dist-info/METADATA
datalogd-0.4.2.dist-info/WHEEL
datalogd-0.4.2.dist-info/entry_points.txt
datalogd-0.4.2.dist-info/top_level.txt
datalogd-0.4.2.dist-info/RECORD
