Metadata-Version: 2.1
Name: datalogd
Version: 0.4.2
Summary: A data logging daemon, easily customisable using a flexible plugin system.
Home-page: https://gitlab.com/ptapping/datalogd
Author: Patrick Tapping
Author-email: mail@patricktapping.com
Project-URL: Documentation, https://datalogd.readthedocs.io/
Project-URL: Source, https://gitlab.com/ptapping/datalogd
Project-URL: Tracker, https://gitlab.com/ptapping/datalogd/-/issues
Classifier: Programming Language :: Python :: 3
Classifier: License :: OSI Approved :: MIT License
Classifier: Operating System :: OS Independent
Requires-Python: >=3.7
License-File: LICENSE.txt
Requires-Dist: wheel
Requires-Dist: pluginlib
Requires-Dist: pydot
Requires-Dist: appdirs
